Metadata-Version: 2.4
Name: qubership-pipelines-common-library
Version: 2.0.2
Summary: Qubership Pipelines common library
License: Apache-2.0
License-File: LICENSE
Author: Qubership
Requires-Python: >=3.11,<4.0
Classifier: License :: OSI Approved :: Apache Software License
Classifier: Programming Language :: Python :: 3
Classifier: Programming Language :: Python :: 3.11
Classifier: Programming Language :: Python :: 3.12
Classifier: Programming Language :: Python :: 3.13
Classifier: Programming Language :: Python :: 3.14
Requires-Dist: GitPython (>=3.1.43,<4.0.0)
Requires-Dist: boto3 (>=1.39.4,<2.0.0)
Requires-Dist: click (>=8.1.7,<9.0.0)
Requires-Dist: ghapi (>=1.0.6,<2.0.0)
Requires-Dist: google-cloud-artifact-registry (>=1.16.1,<2.0.0)
Requires-Dist: http-exceptions (>=0.2.10,<0.3.0)
Requires-Dist: kubernetes (>=34.1.0,<35.0.0)
Requires-Dist: minio (>=7.2.12,<8.0.0)
Requires-Dist: python-gitlab (>=4.13.0,<5.0.0)
Requires-Dist: python-jenkins (>=1.8.2,<2.0.0)
Requires-Dist: pyyaml (>=6.0.2,<7.0.0)
Requires-Dist: requests (>=2.32.3,<3.0.0)
Requires-Dist: rich (>=14.2.0,<15.0.0)
Requires-Dist: urllib3 (>=2.2.3,<3.0.0)
Requires-Dist: webexpythonsdk (==2.0.1)
